Metadata-Version: 1.0
Name: Reverse4343
Version: 1.0.0
Summary: This is a reverse shell, if you find this in your system consider it compromised
Home-page: UNKNOWN
Author: isHaacK
Author-email: UNKNOWN
License: UNKNOWN
Platform: UNKNOWN
